README.rst
setup.cfg
setup.py
webtest_casperjs/__init__.py
webtest_casperjs.egg-info/PKG-INFO
webtest_casperjs.egg-info/SOURCES.txt
webtest_casperjs.egg-info/dependency_links.txt
webtest_casperjs.egg-info/entry_points.txt
webtest_casperjs.egg-info/not-zip-safe
webtest_casperjs.egg-info/requires.txt
webtest_casperjs.egg-info/top_level.txt