Metadata-Version: 1.1
Name: webtest-casperjs
Version: 0.2
Summary: Use casperjs with WebTest
Home-page: https://github.com/gawel/webtest-casperjs
Author: Gael Pasgrimaud
Author-email: gael@gawel.org
License: MIT
Keywords: wsgi test unit tests web casperjs
Platform: UNKNOWN
Classifier: Development Status :: 5 - Production/Stable
Classifier: Framework :: Paste
Classifier: Intended Audience :: Developers
Classifier: License :: OSI Approved :: MIT License
Classifier: Topic :: Internet :: WWW/HTTP :: WSGI
Classifier: Topic :: Internet :: WWW/HTTP :: WSGI :: Server
Classifier: Programming Language :: Python :: 2.6
Classifier: Programming Language :: Python :: 2.7
Classifier: Programming Language :: Python :: 3
Classifier: Programming Language :: Python :: 3.2
Classifier: Programming Language :: Python :: 3.3
